[
  {
    "family": "MaterialIcons",
    "fonts": [
      {
        "asset": "https://fonts.gstatic.com/s/materialicons/v42/flUhRq6tzZclQEJ-Vdg-IuiaDsNcIhQ8tQ.woff2"
      }
    ]
  },
  {
    "family": "GoogleSans",
    "fonts": [
      {
        "asset": "fonts/GoogleSans-Regular.ttf"
      }
    ]
  },
  {
    "family": "GalleryIcons",
    "fonts": [
      {
        "asset": "fonts/GalleryIcons.ttf"
      }
    ]
  },
  {
    "family": "AbrilFatface",
    "fonts": [
      {
        "asset": "fonts/AbrilFatface-Regular.ttf"
      }
    ]
  },
  {
    "family": "LibreFranklin",
    "fonts": [
      {
        "asset": "fonts/LibreFranklin-Regular.ttf"
      }
    ]
  },
  {
    "family": "Merriweather",
    "fonts": [
      {
        "asset": "fonts/Merriweather-Regular.ttf"
      }
    ]
  },
  {
    "family": "Raleway",
    "fonts": [
      {
        "asset": "fonts/Raleway-Regular.ttf"
      }
    ]
  },
  {
    "family": "Roboto",
    "fonts": [
      {
        "asset": "fonts/Roboto-Regular.ttf"
      },
      {
        "asset": "fonts/Roboto-Thin.ttf",
        "weight": 300
      },
      {
        "asset": "fonts/Roboto-Light.ttf",
        "weight": 400
      },
      {
        "asset": "fonts/Roboto-Medium.ttf",
        "weight": 500
      },
      {
        "asset": "fonts/Roboto-Bold.ttf",
        "weight": 700
      },
      {
        "asset": "fonts/Roboto-Black.ttf",
        "weight": 800
      }
    ]
  },
  {
    "family": "MaterialIcons",
    "fonts": [
      {
        "asset": "fonts/MaterialIcons-Regular.ttf"
      }
    ]
  }
]
